s1302003_learn/__init__.py
s1302003_learn/statistics/__init__.py
s1302003_learn/statistics/itemFequencies.py
s1302003_learn/visualization/__init__.py
s1302003_learn/visualization/heatMap.py
s1302003_learn-2025.7.29.1.dist-info/License.txt
s1302003_learn-2025.7.29.1.dist-info/METADATA
s1302003_learn-2025.7.29.1.dist-info/WHEEL
s1302003_learn-2025.7.29.1.dist-info/top_level.txt
s1302003_learn-2025.7.29.1.dist-info/RECORD
