Metadata-Version: 2.1
Name: s1302003_learn
Version: 2025.7.29.1
Summary: This is a test software for class work.
Home-page: https://github.com/SatvG/s1302003_learn
Author: Satvik GANESH
Author-email: satvikganesh@gmail.com
License: GPLv3
Classifier: Development Status :: 4 - Beta
Classifier: Programming Language :: Python :: 3
Classifier: License :: OSI Approved :: GNU General Public License v3 (GPLv3)
Classifier: Operating System :: OS Independent
Requires-Python: >=3.5
License-File: License.txt
Requires-Dist: pami
